{
  "workers": [
    {
      "name": "resfs",
      "last_name": "dsfdsfds",
      "phone": "+79888888888",
      "email": "dsfsdfds@ddsfds.rtu",
      "position": "44",
      "id": 1
    },
    {
      "name": "dfsds",
      "last_name": "dsfsdfds",
      "phone": "+79993333333",
      "email": "fesfdsfc@tre.ru",
      "position": "5",
      "id": 2
    }
  ],
  "goods_monitor": [
    {
      "articul": "2",
      "name": "Кофта",
      "type": "Одежда",
      "count": "100",
      "id": 2
    },
    {
      "articul": "1",
      "name": "Зонтик",
      "type": "Аксессуары ",
      "count": "200",
      "id": 3
    }
  ],
  "users": [
    {
      "email": "lbvfzx@gmail.com",
      "password": "$2a$10$.nafdfoFen5wAZWpo7i4yeK7KNsmMjBD.8gyLLdj0O4dtyQCPvTEm",
      "name": "Ivan",
      "last_name": "Kozlov",
      "id": 1
    }
  ],
  "login": []
}